factorial_app/__init__.py
factorial_app/app.py
factorial_app/factorial.py
factorial_app/requirements.txt
factorial_app-0.1.2.dist-info/METADATA
factorial_app-0.1.2.dist-info/WHEEL
factorial_app-0.1.2.dist-info/RECORD
