Metadata-Version: 2.1
Name: factorial-app
Version: 0.1.2
Summary: 
Author: niran
Author-email: vnmduc6420@gmail.com
Requires-Python: >=3.10,<4.0
Classifier: Programming Language :: Python :: 3
Classifier: Programming Language :: Python :: 3.10
Classifier: Programming Language :: Python :: 3.11
Classifier: Programming Language :: Python :: 3.12
Requires-Dist: streamlit (>=1.32.2,<2.0.0)
